claircontroller/__init__.py
claircontroller/command_line.py
claircontroller/controller.py
claircontroller/server.py
claircontroller/setup.py
claircontroller/test_controller.py
claircontroller/version.py
claircontroller/client/__init__.py
claircontroller/client/api_client.py
claircontroller/client/configuration.py
claircontroller/client/rest.py
claircontroller/client/apis/__init__.py
claircontroller/client/apis/vulnerability_getup_io_v1_api.py
claircontroller/client/models/__init__.py
claircontroller/client/models/unversioned_list_meta.py
claircontroller/client/models/v1_clair_report.py
claircontroller/client/models/v1_clair_report_list.py
claircontroller/client/models/v1_clair_report_tag.py
claircontroller/client/models/v1_clair_report_vulnerability.py
claircontroller/client/models/v1_delete_options.py
claircontroller/client/models/v1_object_meta.py
claircontroller/client/models/v1_owner_reference.py
claircontroller/test/__init__.py
claircontroller/test/test_third_party_resources_api.py
claircontroller/test/test_unversioned_list_meta.py
claircontroller/test/test_v1_clair_report.py
claircontroller/test/test_v1_clair_report_image_stream_tag.py
claircontroller/test/test_v1_clair_report_list.py
claircontroller/test/test_v1_clair_report_tag.py
claircontroller/test/test_v1_clair_report_vulnerability.py
claircontroller/test/test_v1_delete_options.py
claircontroller/test/test_v1_object_meta.py
claircontroller/test/test_v1_owner_reference.py
claircontroller/test/test_vulnerability_getup_io_v1_api.py
claircontroller/test/test_vulnerability_getup_io_v1alpha1_api.py
claircontroller-0.0.1rc4.dist-info/DESCRIPTION.rst
claircontroller-0.0.1rc4.dist-info/METADATA
claircontroller-0.0.1rc4.dist-info/RECORD
claircontroller-0.0.1rc4.dist-info/WHEEL
claircontroller-0.0.1rc4.dist-info/entry_points.txt
claircontroller-0.0.1rc4.dist-info/metadata.json
claircontroller-0.0.1rc4.dist-info/top_level.txt
