Metadata-Version: 2.0
Name: claircontroller
Version: 0.0.1rc4
Summary: Openshift Clair Controller
Home-page: https://github.com/caruccio/client-python
Author: Mateus Caruccio
Author-email: mateus.caruccio@getupcloud.com
License: Apache License Version 2.0
Platform: UNKNOWN
Requires-Dist: kontroller (==0.0.2)
Requires-Dist: openshift-client-python (==2.0.0)
